SemiX/Transistor.py
SemiX/__init__.py
SemiX/diode.py
semix-0.1.2.dist-info/licenses/LICENSE
semix-0.1.2.dist-info/METADATA
semix-0.1.2.dist-info/WHEEL
semix-0.1.2.dist-info/top_level.txt
semix-0.1.2.dist-info/RECORD
